flask_mux/__init__.py
flask_mux/errors.py
flask_mux/mux.py
flask_mux/router.py
Flask_Mux-0.0.3.dist-info/LICENSE
Flask_Mux-0.0.3.dist-info/METADATA
Flask_Mux-0.0.3.dist-info/WHEEL
Flask_Mux-0.0.3.dist-info/top_level.txt
Flask_Mux-0.0.3.dist-info/RECORD
