Metadata-Version: 2.1
Name: Flask-Mux
Version: 0.0.3
Summary: Minimal routing extension for Flask
Home-page: https://github.com/ElMehdi19/flask-mux
Author: El Mehdi Rami
Author-email: elmehdirami5@gmail.com
License: UNKNOWN
Project-URL: Documentation, https://flask-mux.readthedocs.com
Project-URL: Source Code, https://github.com/ElMehdi19
Platform: UNKNOWN
Classifier: Development Status :: 5 - Production/Stable
Classifier: Environment :: Web Environment
Classifier: Intended Audience :: Developers
Classifier: License :: OSI Approved :: MIT License
Classifier: Operating System :: OS Independent
Classifier: Programming Language :: Python
Classifier: Programming Language :: Python :: 3
Classifier: Programming Language :: Python :: 3.6
Classifier: Programming Language :: Python :: 3.7
Classifier: Programming Language :: Python :: 3.8
Classifier: Programming Language :: Python :: 3.9
Classifier: Topic :: Internet :: WWW/HTTP :: Dynamic Content
Requires-Python: >=3.6
Requires-Dist: flask
